docs/.prapticonfig.md
docs/config_files.md
docs/editor_tweaks.md
docs/local_llms.md
docs/prapti_spec.md
docs/user_guide.md
prapti/__init__.py
prapti/__main__.py
prapti/__version__.py
prapti/__pycache__/__init__.cpython-310.pyc
prapti/__pycache__/__version__.cpython-310.pyc
prapti/core/__init__.py
prapti/core/_core_execution_state.py
prapti/core/action.py
prapti/core/builtins.py
prapti/core/chat_markdown_parser.py
prapti/core/command_interpreter.py
prapti/core/command_message.py
prapti/core/configuration.py
prapti/core/execution_state.py
prapti/core/hooks.py
prapti/core/load_configuration.py
prapti/core/logger.py
prapti/core/plugin.py
prapti/core/responder.py
prapti/core/source_location.py
prapti/core/__pycache__/__init__.cpython-310.pyc
prapti/core/__pycache__/_core_execution_state.cpython-310.pyc
prapti/core/__pycache__/action.cpython-310.pyc
prapti/core/__pycache__/builtins.cpython-310.pyc
prapti/core/__pycache__/chat_markdown_parser.cpython-310.pyc
prapti/core/__pycache__/command_interpreter.cpython-310.pyc
prapti/core/__pycache__/command_message.cpython-310.pyc
prapti/core/__pycache__/configuration.cpython-310.pyc
prapti/core/__pycache__/execution_state.cpython-310.pyc
prapti/core/__pycache__/hooks.cpython-310.pyc
prapti/core/__pycache__/load_configuration.cpython-310.pyc
prapti/core/__pycache__/logger.cpython-310.pyc
prapti/core/__pycache__/plugin.cpython-310.pyc
prapti/core/__pycache__/responder.cpython-310.pyc
prapti/core/__pycache__/source_location.cpython-310.pyc
prapti/plugins/__init__.py
prapti/plugins/agents_test_1.md
prapti/plugins/experimental_agents.py
prapti/plugins/experimental_gitlog.py
prapti/plugins/include.py
prapti/plugins/prapti_test_actions.md
prapti/plugins/prapti_test_actions.py
prapti/plugins/prapti_test_config.py
prapti/plugins/prapti_test_responder.py
prapti/plugins/__pycache__/__init__.cpython-310.pyc
prapti/plugins/__pycache__/experimental_agents.cpython-310.pyc
prapti/plugins/__pycache__/experimental_gitlog.cpython-310.pyc
prapti-0.0.2.dist-info/LICENSE
prapti-0.0.2.dist-info/METADATA
prapti-0.0.2.dist-info/WHEEL
prapti-0.0.2.dist-info/entry_points.txt
prapti-0.0.2.dist-info/top_level.txt
prapti-0.0.2.dist-info/RECORD
