Metadata-Version: 2.1
Name: prapti
Version: 0.0.2
Summary: Converse with LLMs directly in markdown files
Author: Ross Bencina, Scott Brewer
License: MIT License
Project-URL: Homepage, https://github.com/prapti-ai/prapti
Project-URL: Documentation, https://github.com/prapti-ai/prapti
Project-URL: Repository, https://github.com/prapti-ai/prapti.git
Keywords: ai,ChatGPT,markdown
Classifier: Programming Language :: Python
Classifier: Programming Language :: Python :: 3
Classifier: Intended Audience :: End Users/Desktop
Classifier: Development Status :: 3 - Alpha
Classifier: Environment :: Console
Classifier: License :: OSI Approved :: MIT License
Classifier: Topic :: Text Processing :: Markup :: Markdown
Requires-Python: >=3.10
License-File: LICENSE
Requires-Dist: pydantic >=2.1.1
Requires-Dist: requests >=2.28.1
Requires-Dist: openai >=0.27.6
Requires-Dist: tiktoken >=0.4.0
Requires-Dist: gpt4all >=1.0.2
Provides-Extra: test
Requires-Dist: pytest >=7.4 ; extra == 'test'
Requires-Dist: pytest-check-links >=0.9 ; extra == 'test'
